{
    "doc_types":
    {
        "a4":
        {
            "header":
            {
                "ruc": "RUC",
                "sales_receipt": "Boleta de Venta Electrónica"
            },
            "client":
            {
                "name":"Cliente",
                "dni":"N° de documento",
                "address":"Domicilio Fiscal",
                "cashier":"Cajero",
                "issue_date":"Fecha emisión",
                "pay_conditions":"Condiciones Pago"
            },
            "products":
            {
                "code":"Código",
                "description":"Descripción",
                "unit":"Unidad",
                "quantity":"Cantidad",
                "unit_value":"Valor Unitario",
                "sale_value":"Valor Venta"
            },
            "checkout":
            {
                "text":"SON",
                "subtotal":"SUB TOTAL",
                "discount":"Descuento",
                "igv":"I.G.V",
                "icbper":"ICBPER",
                "total":"TOTAL",
                "product_quantity":"Cantidad de Productos",
                "cash":"Efectivo",
                "change":"Vuelto",
                "transfer":"Transferencia",
                "card":"Tarjeta",
                "balance_payable":"Saldo por pagar"
            },
            "footer":
            {
                "thanks":"Agradecimiento"
            }
        },
        "ticket":
        {
            "header":
            {
                "issue_date":"Fecha emisión"
            },
            "client":
            {
                "name":"Cliente",
                "dni_ruc":"DNI/RUC",
                "address":"Dirección"
            },
            "products":
            {
                "table":
                {
                    "quantity": "CANT.",
                    "unit":"UNID.",
                    "product":"PRODUCTO",
                    "unit_price":"P.UNIT",
                    "amount":"IMPORTE"
                }
            },
            "checkout":
            {
                "subtotal":"SUB TOTAL",
                "discount":"Descuento",
                "igv":"I.G.V",
                "icbper":"ICBPER",
                "total":"TOTAL",
                "text":"SON"
            },
            "doc_reference":
            {
                "title":"Doc. Referencia",
                "reason":"Motivo",
                "reference":"Referencia",
                "issue_date":"Fecha emisión"
            },
            "additional":
            {
                "product_quantity":"Cantidad de Productos",
                "phone":"Teléfono"
            },
            "footer":
            {
                "cashier":"Caja",
                "address":"Domicilio Fiscal",
                "message":"La representación impresa del comprobante electrónico puede ser consultado en",
                "thanks":"GRACIAS POR SU COMPRA"
            }
        }
    },
    "pages":
    {
        "bills":
        {
            "title":"Facturas",
            "total":"Total",
            "search_placeholder":"Buscar por Número de Documento / Respuesta CDR",
            "tabs":
            {
                "accepted":
                {
                    "tabname":"Aceptados",
                    "table":
                    {
                        "doc_number":"Número de Documento",
                        "amount":"Monto",
                        "date":"Fecha",
                        "cdr_response":"Respuesta CDR",
                        "cdr_code":"Código CDR",
                        "state":"Estado",
                        "xml":"XML"
                    }
                },
                "pending":
                {
                    "tabname":"Pendientes",
                    "table":
                    {
                        "doc_number":"Número de Documento",
                        "amount":"Monto",
                        "date":"Fecha",
                        "cdr_response":"Respuesta CDR",
                        "cdr_code":"Código CDR",
                        "state":"Estado",
                        "xml":"XML"
                    }
                },
                "rejected":
                {
                    "tabname":"Rechazados",
                    "table":
                    {
                        "doc_number":"Número de Documento",
                        "amount":"Monto",
                        "date":"Fecha",
                        "cdr_response":"Respuesta CDR",
                        "cdr_code":"Código CDR",
                        "state":"Estado",
                        "xml":"XML"
                    }
                },
                "cancelled":
                {
                    "tabname":"Anulados",
                    "table":
                    {
                        "doc_number":"Número de Documento",
                        "amount":"Monto",
                        "date":"Fecha",
                        "cdr_response":"Respuesta CDR",
                        "cdr_code":"Código CDR",
                        "state":"Estado",
                        "xml":"XML"
                    }
                }
            }
        }
    }
}